components/combinational_components/adder.v
module adder (out, in1, in2);

    input [31:0] in1 , in2;
    output [31:0] out;

    assign out = in1 + in2;

endmodule

combinational_components/mux.v
module mux (out, in1 , in2, sel);
    
    input sel;
    input [31:0] in1,in2;
    output reg [31:0] out;
    
    always@(sel or in1 or in2)
    case (sel)
      0: out <= in1;
      1: out <= in2;
    endcase
    
endmodule

components/state_components/instruction_memory.v
module instruction_memory(clk, readAddress, instruction);
input clk;
input [31:0] readAddress;

output reg [31:0] instruction;

reg [7:0]memory [1023:0] ;

initial begin
	{memory[0],memory[1],memory[2],memory[3]} = 'h2149FF00;
	{memory[4],memory[5],memory[6],memory[7]}= 'h2149FF04;
	{memory[8],memory[9],memory[10],memory[11]} = 'h014B4808;
	{memory[12],memory[13],memory[14],memory[15]} = 'h014B4812; 
	{memory[16],memory[17],memory[18],memory[19]} = 'h014B4816; //add t1 t2 t3
	{memory[48],memory[49],memory[50],memory[51]} = 'h2149FF48; // addi t1 t2 0xffff
end

always @(posedge clk)
begin
	instruction <= {memory[readAddress[9:0]], memory[readAddress[9:0]+1], memory[readAddress[9:0]+2], memory[readAddress[9:0]+3]};
end

endmodule

Main/fetch.v
module fetch(instruction, pc_out, pcSrc, clk, pc_branched );

// clock, pc source
input wire clk, pcSrc; 
// branched pc
input wire [31:0] pc_branched;

wire [31:0] pcOut_mux, mux_pc;
// pc register
reg [31:0] pc, input_4 ;
output wire [31:0] instruction , pc_out; 


initial begin
  input_4 = 4;
  pc = 0;
end

always@(posedge clk) pc <= mux_pc;

assign pc_out = pcOut_mux;
//  get instruction using address in pc
instruction_memory im(clk, pc, instruction);

// MUX
mux mux(mux_pc,pcOut_mux, pc_branched, pcSrc);

// ADDER 
adder add(pcOut_mux, pc, input_4);

endmodule

tests/fetch_test.v

module fetch_test;

reg clk, pcSrc;
reg [31:0] pc_branched;
wire [31:0] instruction, pc_out;

fetch f(instruction, pc_out, pcSrc, clk, pc_branched);

initial begin
    clk= 0;
    forever begin
        #5 clk = ~clk;
    end
end

initial begin
    $dumpfile("tests/simulation/fetch_test.vcd");    
    $dumpvars(0, f);
    $monitor("clk: %b, instruction: %h, pc_out: %d, pc_branched: %d, pcSrc: %b", clk, instruction, pc_out, pc_branched, pcSrc);
end

initial fork
    #0 begin pcSrc <= 1;pc_branched = 0;end 
    #5 begin pcSrc <= 0; end
    #45 begin  pcSrc <= 1; pc_branched = 8; end
    #55 begin pcSrc <= 0; end
join


initial
    #75 $finish;

endmodule

tests/simulation/fetch_test.vcd
$date
	Tue Apr 25 15:42:30 2017
$end
$version
	Icarus Verilog
$end
$timescale
	1s
$end
$scope module fetch_test $end
$scope module f $end
$var wire 1 ! clk $end
$var wire 1 " pcSrc $end
$var wire 32 # pc_branched [31:0] $end
$var wire 32 $ pc_out [31:0] $end
$var wire 32 % pcOut_mux [31:0] $end
$var wire 32 & mux_pc [31:0] $end
$var wire 32 ' instruction [31:0] $end
$var reg 32 ( input_4 [31:0] $end
$var reg 32 ) pc [31:0] $end
$scope module add $end
$var wire 32 * in1 [31:0] $end
$var wire 32 + in2 [31:0] $end
$var wire 32 , out [31:0] $end
$upscope $end
$scope module im $end
$var wire 1 ! clk $end
$var wire 32 - readAddress [31:0] $end
$var reg 32 . instruction [31:0] $end
$upscope $end
$scope module mux $end
$var wire 32 / in1 [31:0] $end
$var wire 32 0 in2 [31:0] $end
$var wire 1 " sel $end
$var reg 32 1 out [31:0] $end
$upscope $end
$upscope $end
$upscope $end
$enddefinitions $end
#0
$dumpvars
b0 1
b0 0
b100 /
bx .
b0 -
b100 ,
b100 +
b0 *
b0 )
b100 (
bx '
b0 &
b100 %
b100 $
b0 #
1"
0!
$end
#5
b100 &
b100 1
b100001010010011111111100000000 '
b100001010010011111111100000000 .
0"
1!
#10
0!
#15
b1000 &
b1000 1
b1000 $
b1000 %
b1000 ,
b1000 /
b100 )
b100 *
b100 -
1!
#20
0!
#25
b1100 &
b1100 1
b100001010010011111111100000100 '
b100001010010011111111100000100 .
b1100 $
b1100 %
b1100 ,
b1100 /
b1000 )
b1000 *
b1000 -
1!
#30
0!
#35
b10000 &
b10000 1
b10000 $
b10000 %
b10000 ,
b10000 /
b1100 )
b1100 *
b1100 -
b1010010110100100000001000 '
b1010010110100100000001000 .
1!
#40
0!
#45
b1000 &
b1000 1
b1010010110100100000010010 '
b1010010110100100000010010 .
b10100 $
b10100 %
b10100 ,
b10100 /
b10000 )
b10000 *
b10000 -
1"
1!
b1000 #
b1000 0
#50
0!
#55
b1100 &
b1100 1
b1100 $
b1100 %
b1100 ,
b1100 /
b1000 )
b1000 *
b1000 -
b1010010110100100000010110 '
b1010010110100100000010110 .
0"
1!
#60
0!
#65
b10000 &
b10000 1
b1010010110100100000001000 '
b1010010110100100000001000 .
b10000 $
b10000 %
b10000 ,
b10000 /
b1100 )
b1100 *
b1100 -
1!
#70
0!
#75
b10100 &
b10100 1
b10100 $
b10100 %
b10100 ,
b10100 /
b10000 )
b10000 *
b10000 -
b1010010110100100000010010 '
b1010010110100100000010010 .
1!
